nsqdriver/NS_CST.py
nsqdriver/NS_DDS_v3.py
nsqdriver/NS_MCI.py
nsqdriver/NS_QSYNC.py
nsqdriver/__init__.py
nsqdriver/common.py
nsqdriver/compiler/__init__.py
nsqdriver/compiler/assembler.cpython-312-darwin.so
nsqdriver/compiler/ns_wave.cpython-312-darwin.so
nsqdriver/compiler/ns_wave.pyi
nsqdriver/compiler/py_wave_asm.cpython-312-darwin.so
nsqdriver/compiler/py_wave_asm.pyi
nsqdriver/nswave/__init__.py
nsqdriver/nswave/_asm.pyi
nsqdriver/nswave/_checkers.cpython-312-darwin.so
nsqdriver/nswave/_checkers.pyi
nsqdriver/nswave/_errors.cpython-312-darwin.so
nsqdriver/nswave/_errors.pyi
nsqdriver/nswave/_functions.cpython-312-darwin.so
nsqdriver/nswave/_functions.pyi
nsqdriver/nswave/_ir.cpython-312-darwin.so
nsqdriver/nswave/_ir.pyi
nsqdriver/nswave/_ir_pass.cpython-312-darwin.so
nsqdriver/nswave/_ir_pass.pyi
nsqdriver/nswave/_optimizations.cpython-312-darwin.so
nsqdriver/nswave/_optimizations.pyi
nsqdriver/nswave/_rules.cpython-312-darwin.so
nsqdriver/nswave/_rules.pyi
nsqdriver/nswave/_translate.cpython-312-darwin.so
nsqdriver/nswave/_translate.pyi
nsqdriver/nswave/kernel.cpython-312-darwin.so
nsqdriver/nswave/kernel.pyi
nsqdriver/wrapper/AWG_ADC.py
nsqdriver/wrapper/ND_NSMCI.py
nsqdriver/wrapper/__init__.py
nsqdriver-0.12.61.dist-info/METADATA
nsqdriver-0.12.61.dist-info/WHEEL
nsqdriver-0.12.61.dist-info/top_level.txt
nsqdriver-0.12.61.dist-info/RECORD
