Metadata-Version: 2.1
Name: nsqdriver
Version: 0.12.61
Summary: Q series measurement and control equipment driver interface
Home-page: https://g2hoyqcmh4.feishu.cn/wiki/Jgt1wxlKniveYQkqCgbcJHsMnoe
Classifier: Intended Audience :: Developers
Classifier: Topic :: Scientific/Engineering :: Interface Engine/Protocol Translator
Classifier: Operating System :: MacOS :: MacOS X
Classifier: Operating System :: Microsoft :: Windows
Classifier: Operating System :: POSIX
Classifier: Programming Language :: Python :: 3.8
Classifier: Programming Language :: Python :: 3.9
Classifier: Programming Language :: Python :: 3.10
Classifier: Programming Language :: Python :: 3.11
Classifier: Programming Language :: Python :: 3.12
Requires-Python: >=3.8
Requires-Dist: numpy>=1.18
Requires-Dist: astor>=0.8.1
Provides-Extra: waveforms
Requires-Dist: waveforms; extra == "waveforms"
